CQCC/__init__.py
CQCC/__main__.py
CQCC/cqcc.py
CQT_Toolbox/__init__.py
CQT_Toolbox/cell2mat.py
CQT_Toolbox/cqt.py
CQT_Toolbox/cqtCell2Sparse.py
CQT_Toolbox/nsgcqwin.py
CQT_Toolbox/nsgtf_real.py
CQT_Toolbox/winfuns.py
Py_CQCC-0.1.1.dist-info/METADATA
Py_CQCC-0.1.1.dist-info/WHEEL
Py_CQCC-0.1.1.dist-info/top_level.txt
Py_CQCC-0.1.1.dist-info/RECORD
