Metadata-Version: 2.1
Name: Py-CQCC
Version: 0.1.1
Summary: Python implementation of CQCC
Home-page: https://github.com/ShubhankarKG/Py-CQCC
Author: Shubhankar Gupta
Author-email: shubhankar.gupto.11@gmail.com
License: UNKNOWN
Project-URL: Bug Tracker, https://github.com/ShubhankarKG/Py-CQCC/issues
Platform: UNKNOWN
Classifier: Programming Language :: Python :: 3
Classifier: License :: OSI Approved :: MIT License
Classifier: Operating System :: OS Independent
Requires-Python: >=3.6
